.env.sample
CONTRIBUTING.md
LICENSE
README.md
notoma/__init__.py
notoma/cli.py
notoma/config.py
notoma/core.py
notoma/dev.py
notoma/logging.py
notoma/page.py
notoma/templates/blocks/_bulleted_list.md.j2
notoma/templates/blocks/_callout.md.j2
notoma/templates/blocks/_code.md.j2
notoma/templates/blocks/_header.md.j2
notoma/templates/blocks/_image.md.j2
notoma/templates/blocks/_numbered_list.md.j2
notoma/templates/blocks/_quote.md.j2
notoma/templates/blocks/_subheader.md.j2
notoma/templates/blocks/_subsubheader.md.j2
notoma/templates/blocks/_text.md.j2
notoma/templates/blocks/_todo.md.j2
notoma/templates/blocks/_video.md.j2
notoma/templates/docs-jekyll.md.j2
notoma/templates/post.md.j2
notoma/templates.py
notoma-0.2.9.dist-info/entry_points.txt
notoma-0.2.9.dist-info/LICENSE
notoma-0.2.9.dist-info/WHEEL
notoma-0.2.9.dist-info/METADATA
notoma-0.2.9.dist-info/RECORD
