Metadata-Version: 2.1
Name: notoma
Version: 0.2.9
Summary: Write and publish your blog articles from Notion.
Home-page: https://nategadzhi.github.io/notoma
License: Apache-2.0
Keywords: Notion,blog,markdown
Author: Nate Gadzhibalaev
Author-email: nate@respawn.io
Requires-Python: >=3.8
Classifier: Development Status :: 4 - Beta
Classifier: License :: OSI Approved :: Apache Software License
Classifier: Programming Language :: Python :: 3
Classifier: Programming Language :: Python :: 3.8
Classifier: Programming Language :: Python :: 3.9
Classifier: Typing :: Typed
Requires-Dist: click
Requires-Dist: importlib-metadata (>=1.0,<2.0); python_version < "3.8"
Requires-Dist: jinja2
Requires-Dist: notion (>=0.0.25)
Requires-Dist: python-dotenv
Project-URL: Repository, https://github.com/nategadzhi/notoma
